README.md
setup.py
crayflow/__init__.py
crayflow.egg-info/PKG-INFO
crayflow.egg-info/SOURCES.txt
crayflow.egg-info/dependency_links.txt
crayflow.egg-info/requires.txt
crayflow.egg-info/top_level.txt
crayflow/cache/__init__.py
crayflow/cache/common.py
crayflow/data/__init__.py
crayflow/data/common.py
crayflow/data/concept_learning.py
crayflow/data/image.py
crayflow/data/text.py
crayflow/instances/__init__.py
crayflow/instances/amazon_reviews.py
crayflow/instances/celebA.py
crayflow/instances/cifar.py
crayflow/instances/higgs.py
crayflow/instances/kdd_99.py
crayflow/instances/large_logo_dataset.py
crayflow/instances/mnist.py
crayflow/instances/omniglot.py
crayflow/instances/svhn.py
crayflow/meta/__init__.py
crayflow/meta/common.py
crayflow/meta/configurable.py
crayflow/meta/lang.py
crayflow/meta/meta.py
crayflow/meta/utils.py
crayflow/sources/__init__.py
crayflow/sources/google_drive.py
crayflow/sources/load.py
crayflow/sources/utils.py
crayflow/utils/__init__.py
crayflow/utils/hashing.py