Metadata-Version: 2.1
Name: crayflow
Version: 0.4.1
Summary: Yet another neural network toolkit - dataflow module
Home-page: https://gitlab.com/craynn/crayflow
Author: Maxim Borisyak
Author-email: maximus.been@gmail.com
Maintainer: Maxim Borisyak and contributors
Maintainer-email: maximus.been@gmail.com
License: MIT
Keywords: dataflow
Platform: UNKNOWN
Classifier: Development Status :: 4 - Beta
Classifier: Intended Audience :: Science/Research
Classifier: License :: OSI Approved :: MIT License
Classifier: Programming Language :: Python :: 3
Provides-Extra: test
